Metadata-Version: 2.1
Name: django-pipeline
Version: 4.0.0
Summary: Pipeline is an asset packaging library for Django.
Author-email: Timothée Peignier <timothee.peignier@tryphon.org>
License: MIT
Project-URL: homepage, https://github.com/jazzband/django-pipeline/
Project-URL: documentation, https://django-pipeline.readthedocs.io/
Project-URL: repository, https://github.com/jazzband/django-pipeline
Project-URL: changelog, https://github.com/jazzband/django-pipeline/blob/master/HISTORY.rst
Keywords: django,pipeline,asset,compiling,concatenation,compression,packaging
Classifier: Development Status :: 5 - Production/Stable
Classifier: Environment :: Web Environment
Classifier: Framework :: Django
Classifier: Framework :: Django :: 4.0
Classifier: Framework :: Django :: 4.1
Classifier: Framework :: Django :: 4.2
Classifier: Framework :: Django :: 5.0
Classifier: Framework :: Django :: 5.1
Classifier: Intended Audience :: Developers
Classifier: License :: OSI Approved :: MIT License
Classifier: Operating System :: OS Independent
Classifier: Programming Language :: Python
Classifier: Programming Language :: Python :: 3
Classifier: Programming Language :: Python :: 3 :: Only
Classifier: Programming Language :: Python :: 3.9
Classifier: Programming Language :: Python :: 3.10
Classifier: Programming Language :: Python :: 3.11
Classifier: Programming Language :: Python :: 3.12
Classifier: Programming Language :: Python :: Implementation :: PyPy
Classifier: Topic :: Utilities
Classifier: Topic :: Software Development :: Libraries :: Python Modules
Classifier: Topic :: Internet :: WWW/HTTP
Classifier: Topic :: Internet :: WWW/HTTP :: Dynamic Content
Requires-Python: >=3.9
License-File: LICENSE
License-File: AUTHORS
Requires-Dist: setuptools
Requires-Dist: wheel
Provides-Extra: testing
Requires-Dist: coveralls; extra == "testing"
Requires-Dist: tox; extra == "testing"
Requires-Dist: wheel; extra == "testing"
Requires-Dist: django; extra == "testing"
